README.rst
hashin.py
setup.cfg
setup.py
hashin_pyup.egg-info/PKG-INFO
hashin_pyup.egg-info/SOURCES.txt
hashin_pyup.egg-info/dependency_links.txt
hashin_pyup.egg-info/entry_points.txt
hashin_pyup.egg-info/top_level.txt