Metadata-Version: 1.1
Name: hashin-pyup
Version: 0.7.2
Summary: Edits your requirements.txt by hashing them in
Home-page: https://github.com/peterbe/hashin
Author: Peter Bengtsson
Author-email: mail@peterbe.com
License: MIT
Keywords: pip,repeatable,deploy,deployment,hash,install,installer
Platform: UNKNOWN
Classifier: Intended Audience :: Developers
Classifier: Intended Audience :: System Administrators
Classifier: License :: OSI Approved :: MIT License
Classifier: Programming Language :: Python :: 2.7
Classifier: Programming Language :: Python :: 3
Classifier: Topic :: Software Development :: Build Tools
Classifier: Topic :: System :: Installation/Setup
Classifier: Topic :: System :: Systems Administration
